instrumentools/CAC.py
instrumentools/DSC.py
instrumentools/TEM.py
instrumentools/TGA.py
instrumentools/__init__.py
instrumentools-0.1.3.dist-info/entry_points.txt
instrumentools-0.1.3.dist-info/LICENSE
instrumentools-0.1.3.dist-info/WHEEL
instrumentools-0.1.3.dist-info/METADATA
instrumentools-0.1.3.dist-info/RECORD
